mini_arcade_native_backend/__init__.py
mini_arcade_native_backend/_native.cp310-win_amd64.pyd
mini_arcade_native_backend-0.6.0.dist-info/METADATA
mini_arcade_native_backend-0.6.0.dist-info/WHEEL
mini_arcade_native_backend-0.6.0.dist-info/licenses/LICENSE
mini_arcade_native_backend-0.6.0.dist-info/RECORD
