Metadata-Version: 2.2
Name: mini-arcade-native-backend
Version: 0.6.0
Summary: Native SDL2 backend for mini-arcade-core using SDL2 + pybind11.
Author-Email: Santiago Rincon <rincores@gmail.com>
License: Copyright (c) 2025 Santiago Rincón
Requires-Python: <3.12,>=3.9
Requires-Dist: mini-arcade-core~=1.1
Provides-Extra: dev
Requires-Dist: pytest~=8.3; extra == "dev"
Requires-Dist: pytest-cov~=6.0; extra == "dev"
Requires-Dist: black~=24.10; extra == "dev"
Requires-Dist: isort~=5.13; extra == "dev"
Requires-Dist: mypy~=1.5; extra == "dev"
Requires-Dist: pylint~=3.3; extra == "dev"
